arp_jarvis_tool_registry-0.1.0.dist-info/licenses/LICENSE
tool_registry/__init__.py
tool_registry/__main__.py
tool_registry/catalog.py
tool_registry/json_schema.py
tool_registry/main.py
tool_registry/safe_eval.py
tool_registry/server.py
tool_registry/domains/__init__.py
tool_registry/domains/core.py
arp_jarvis_tool_registry-0.1.0.dist-info/METADATA
arp_jarvis_tool_registry-0.1.0.dist-info/WHEEL
arp_jarvis_tool_registry-0.1.0.dist-info/entry_points.txt
arp_jarvis_tool_registry-0.1.0.dist-info/top_level.txt
arp_jarvis_tool_registry-0.1.0.dist-info/RECORD
