Metadata-Version: 2.4
Name: arp-jarvis-tool-registry
Version: 0.1.0
Summary: Tool Registry service for ARP runtimes (tool discovery, schemas, invocation).
Author: Agent Runtime Protocol
License: MIT License
Project-URL: Repository, https://github.com/AgentRuntimeProtocol/Tool_Registry
Project-URL: Issues, https://github.com/AgentRuntimeProtocol/Tool_Registry/issues
Requires-Python: >=3.10
License-File: LICENSE
Requires-Dist: arp-standard-py<0.2.0,>=0.1.0
Provides-Extra: dev
Requires-Dist: pyright>=1.1.0; extra == "dev"
Requires-Dist: pytest>=7; extra == "dev"
Requires-Dist: pytest-cov>=4; extra == "dev"
Dynamic: license-file
